cldfofflinebrowser/__init__.py
cldfofflinebrowser/media.py
cldfofflinebrowser/osmtiles.py
cldfofflinebrowser/template.py
cldfofflinebrowser/commands/__init__.py
cldfofflinebrowser/commands/add.py
cldfofflinebrowser/commands/create.py
cldfofflinebrowser/static/Leaflet.fullscreen.js
cldfofflinebrowser/static/bootstrap.bundle.min.js
cldfofflinebrowser/static/bootstrap.min.css
cldfofflinebrowser/static/fullscreen.png
cldfofflinebrowser/static/fullscreen@2x.png
cldfofflinebrowser/static/jquery-3.5.1.min.js
cldfofflinebrowser/static/leaflet.css
cldfofflinebrowser/static/leaflet.fullscreen.css
cldfofflinebrowser/static/leaflet.js
cldfofflinebrowser/static/offline.js
cldfofflinebrowser/static/project.css
cldfofflinebrowser/templates/base.html
cldfofflinebrowser/templates/data.js
cldfofflinebrowser/templates/index.html
cldfofflinebrowser/templates/language.html
cldfofflinebrowser/templates/parameter.html
cldfofflinebrowser/tiles/0/0/0.png
cldfofflinebrowser/tiles/1/0/0.png
cldfofflinebrowser/tiles/1/0/1.png
cldfofflinebrowser/tiles/1/1/0.png
cldfofflinebrowser/tiles/1/1/1.png
cldfofflinebrowser/tiles/2/0/0.png
cldfofflinebrowser/tiles/2/0/1.png
cldfofflinebrowser/tiles/2/0/2.png
cldfofflinebrowser/tiles/2/0/3.png
cldfofflinebrowser/tiles/2/1/0.png
cldfofflinebrowser/tiles/2/1/1.png
cldfofflinebrowser/tiles/2/1/2.png
cldfofflinebrowser/tiles/2/1/3.png
cldfofflinebrowser/tiles/2/2/0.png
cldfofflinebrowser/tiles/2/2/1.png
cldfofflinebrowser/tiles/2/2/2.png
cldfofflinebrowser/tiles/2/2/3.png
cldfofflinebrowser/tiles/2/3/0.png
cldfofflinebrowser/tiles/2/3/1.png
cldfofflinebrowser/tiles/2/3/2.png
cldfofflinebrowser/tiles/2/3/3.png
cldfofflinebrowser/tiles/3/0/0.png
cldfofflinebrowser/tiles/3/0/1.png
cldfofflinebrowser/tiles/3/0/2.png
cldfofflinebrowser/tiles/3/0/3.png
cldfofflinebrowser/tiles/3/0/4.png
cldfofflinebrowser/tiles/3/0/5.png
cldfofflinebrowser/tiles/3/0/6.png
cldfofflinebrowser/tiles/3/0/7.png
cldfofflinebrowser/tiles/3/1/0.png
cldfofflinebrowser/tiles/3/1/1.png
cldfofflinebrowser-0.2.0.dist-info/LICENSE
cldfofflinebrowser-0.2.0.dist-info/METADATA
cldfofflinebrowser-0.2.0.dist-info/WHEEL
cldfofflinebrowser-0.2.0.dist-info/entry_points.txt
cldfofflinebrowser-0.2.0.dist-info/top_level.txt
cldfofflinebrowser-0.2.0.dist-info/RECORD
