Metadata-Version: 2.1
Name: cldfofflinebrowser
Version: 0.2.0
Summary: A cldfbench plugin to create offline broweable CLDF datasets
Home-page: https://github.com/cldf/cldfofflinebrowser
Author: 'Robert Forkel and Hans-Jörg Bibiko
Author-email: dlce.rdm@eva.mpg.de
Project-URL: Bug Tracker, https://github.com/cldf/cldfofflinebrowser/issues
Platform: any
Classifier: Development Status :: 4 - Beta
Classifier: Intended Audience :: Developers
Classifier: Intended Audience :: Science/Research
Classifier: Natural Language :: English
Classifier: Operating System :: OS Independent
Classifier: Programming Language :: Python :: 3
Classifier: Programming Language :: Python :: 3.7
Classifier: Programming Language :: Python :: 3.8
Classifier: Programming Language :: Python :: 3.9
Classifier: Programming Language :: Python :: 3.10
Classifier: Programming Language :: Python :: 3.11
Classifier: Programming Language :: Python :: Implementation :: CPython
Classifier: Programming Language :: Python :: Implementation :: PyPy
Classifier: License :: OSI Approved :: Apache Software License
Requires-Python: >=3.7
License-File: LICENSE
Requires-Dist: rfc3986
Requires-Dist: cldfbench
Requires-Dist: tqdm
Requires-Dist: jinja2
Provides-Extra: dev
Requires-Dist: tox ; extra == 'dev'
Requires-Dist: flake8 ; extra == 'dev'
Requires-Dist: wheel (>=0.36) ; extra == 'dev'
Requires-Dist: build ; extra == 'dev'
Requires-Dist: twine ; extra == 'dev'
Provides-Extra: test
Requires-Dist: pytest (>=5) ; extra == 'test'
Requires-Dist: pytest-mock ; extra == 'test'
Requires-Dist: pytest-cov ; extra == 'test'
Requires-Dist: coverage (>=4.2) ; extra == 'test'
